tt3de-0.1.0.dist-info/METADATA
tt3de-0.1.0.dist-info/WHEEL
tt3de.libs/libgcc_s-b5472b99.so.1
tt3de/textual_widget.py
tt3de/__init__.py
tt3de/asset_load.py
tt3de/glm_camera.py
tt3de/asset_fastloader.py
tt3de/richtexture.py
tt3de/tt_2dnodes.py
tt3de/render_context_rust.py
tt3de/tt_3dnodes.py
tt3de/utils.py
tt3de/textual/__init__.py
tt3de/textual/widgets.py
tt3de/points.py
tt3de/prefab3d.py
tt3de/tt3de.pypy310-pp73-x86-linux-gnu.so
tt3de-0.1.0.dist-info/RECORD
