Metadata-Version: 2.3
Name: tt3de
Version: 0.1.0
